matchcode_toolkit/__init__.py
matchcode_toolkit/fingerprinting.py
matchcode_toolkit/plugin_fingerprint.py
matchcode_toolkit/stemming.py
matchcode_toolkit/pipelines/__init__.py
matchcode_toolkit/pipelines/fingerprint_codebase.py
matchcode_toolkit/pipelines/scan_and_fingerprint_package.py
matchcode_toolkit-7.2.2.dist-info/AUTHORS.rst
matchcode_toolkit-7.2.2.dist-info/CHANGELOG.rst
matchcode_toolkit-7.2.2.dist-info/CODE_OF_CONDUCT.rst
matchcode_toolkit-7.2.2.dist-info/METADATA
matchcode_toolkit-7.2.2.dist-info/NOTICE
matchcode_toolkit-7.2.2.dist-info/WHEEL
matchcode_toolkit-7.2.2.dist-info/apache-2.0.LICENSE
matchcode_toolkit-7.2.2.dist-info/entry_points.txt
matchcode_toolkit-7.2.2.dist-info/top_level.txt
matchcode_toolkit-7.2.2.dist-info/RECORD
