Metadata-Version: 2.2
Name: matchcode-toolkit
Version: 7.2.2
Summary: matchcode-toolkit
Home-page: https://github.com/aboutcode-org/matchcode-toolkit
Author: nexB. Inc. and others
Author-email: info@aboutcode.org
License: Apache-2.0
Keywords: matchcode,ScanCode.io,open source
Classifier: Development Status :: 5 - Production/Stable
Classifier: Intended Audience :: Developers
Classifier: Programming Language :: Python :: 3
Classifier: Programming Language :: Python :: 3 :: Only
Classifier: Topic :: Software Development
Classifier: Topic :: Utilities
Requires-Python: >=3.9
License-File: apache-2.0.LICENSE
License-File: NOTICE
License-File: AUTHORS.rst
License-File: CHANGELOG.rst
License-File: CODE_OF_CONDUCT.rst
Requires-Dist: bitarray
Requires-Dist: commoncode
Requires-Dist: plugincode
Requires-Dist: samecode
Requires-Dist: typecode
Requires-Dist: tree-sitter
Requires-Dist: tree-sitter-c
Requires-Dist: tree-sitter-cpp
Requires-Dist: tree-sitter-go
Requires-Dist: tree-sitter-java
Requires-Dist: tree-sitter-javascript
Requires-Dist: tree-sitter-python
Requires-Dist: tree-sitter-rust
Provides-Extra: testing
Requires-Dist: pytest!=7.0.0,>=6; extra == "testing"
Requires-Dist: pytest-xdist>=2; extra == "testing"
Requires-Dist: aboutcode-toolkit>=7.0.2; extra == "testing"
Requires-Dist: pycodestyle>=2.8.0; extra == "testing"
Requires-Dist: twine; extra == "testing"
Requires-Dist: black; extra == "testing"
Requires-Dist: isort; extra == "testing"
Requires-Dist: scancode-toolkit; extra == "testing"
Provides-Extra: docs
Requires-Dist: Sphinx>=5.0.2; extra == "docs"
Requires-Dist: sphinx-rtd-theme>=1.0.0; extra == "docs"
Requires-Dist: sphinx-reredirects>=0.1.2; extra == "docs"
Requires-Dist: doc8>=0.11.2; extra == "docs"
Requires-Dist: sphinx-autobuild; extra == "docs"
Requires-Dist: sphinx-rtd-dark-mode>=1.3.0; extra == "docs"
Requires-Dist: sphinx-copybutton; extra == "docs"
